eeganalyzer/__init__.py
eeganalyzer/cli/__init__.py
eeganalyzer/cli/cli.py
eeganalyzer/core/__init__.py
eeganalyzer/core/array_processor.py
eeganalyzer/core/csv_processor.py
eeganalyzer/core/eeg_processor.py
eeganalyzer/core/processor.py
eeganalyzer/utils/__init__.py
eeganalyzer/utils/buttler.py
eeganalyzer/utils/config.py
eeganalyzer/utils/database.py
eeganalyzer_scico-0.1.1.dist-info/licenses/LICENSE
gui/__init__.py
gui/run_metrics_viewer.py
gui/metrics_viewer/__init__.py
gui/metrics_viewer/app.py
gui/metrics_viewer/database_handler.py
gui/metrics_viewer/mne_plot_helper.py
gui/metrics_viewer/plot_frame.py
gui/metrics_viewer/selection_frame.py
gui/metrics_viewer/utils.py
eeganalyzer_scico-0.1.1.dist-info/METADATA
eeganalyzer_scico-0.1.1.dist-info/WHEEL
eeganalyzer_scico-0.1.1.dist-info/entry_points.txt
eeganalyzer_scico-0.1.1.dist-info/top_level.txt
eeganalyzer_scico-0.1.1.dist-info/RECORD
