Metadata-Version: 2.4
Name: eeganalyzer-scico
Version: 0.1.1
Summary: A comprehensive tool for analyzing and visualizing EEG data with focus on customizable metric analysis
Author-email: SoenkevL <soenke.v.l@outlook.com>
License-Expression: GPL-3.0-or-later
Project-URL: Homepage, https://github.com/SoenkevL/EEGAnalyzer
Project-URL: Bug Tracker, https://github.com/SoenkevL/EEGAnalyzer/issues
Classifier: Programming Language :: Python :: 3
Classifier: Operating System :: OS Independent
Classifier: Topic :: Scientific/Engineering :: Medical Science Apps.
Classifier: Topic :: Scientific/Engineering :: Bio-Informatics
Requires-Python: >=3.8
License-File: LICENSE
Requires-Dist: edgeofpy==0.0.1
Requires-Dist: icecream==2.1.3
Requires-Dist: customtkinter==5.2.2
Requires-Dist: mat4py==0.6.0
Requires-Dist: matplotlib==3.9.2
Requires-Dist: mne==1.8.0
Requires-Dist: mne-qt-browser==0.6.3
Requires-Dist: multiprocesspandas==1.1.5
Requires-Dist: neurokit2==0.2.10
Requires-Dist: numpy==1.26.4
Requires-Dist: pandas==2.2.3
Requires-Dist: powerlaw==1.5
Requires-Dist: PyYAML==6.0.2
Requires-Dist: PyQt6==6.7.1
Requires-Dist: scipy==1.14.1
Requires-Dist: SQLAlchemy>=2.0.40
Dynamic: license-file
